pxinteract/__init__.py
pxinteract-0.1.dist-info/LICENSE
pxinteract-0.1.dist-info/METADATA
pxinteract-0.1.dist-info/WHEEL
pxinteract-0.1.dist-info/top_level.txt
pxinteract-0.1.dist-info/RECORD
