Metadata-Version: 2.1
Name: pxinteract
Version: 0.1
Summary: Execute and Interact With Programme or Commands using Python
Home-page: https://github.com/aencode/PXinteract
Author: Ashish Rana
Author-email: aencodein@gmail.com
License: UNKNOWN
Platform: UNKNOWN
